audio_similarity/__init__.py
audio_similarity/audio_processor.py
audio_similarity/index_factory.py
audio_similarity/utils.py
audio_similarity/version.py
audio_similarity/visualization.py
anirudhp_audio_similarity-0.1.0.dist-info/METADATA
anirudhp_audio_similarity-0.1.0.dist-info/WHEEL
anirudhp_audio_similarity-0.1.0.dist-info/licenses/LICENSE
anirudhp_audio_similarity-0.1.0.dist-info/RECORD
