Metadata-Version: 2.3
Name: anirudhp-audio-similarity
Version: 0.1.0
Summary: A package for audio similarity analysis
Author-email: Anirudh Praveen <anirudhpraveen2000@gmail.com>
License: MIT License
Requires-Python: >=3.8
Requires-Dist: numpy
Requires-Dist: scipy
Requires-Dist: torch
Requires-Dist: torchaudio
Provides-Extra: cpu
Requires-Dist: faiss-cpu>=1.7.0; extra == 'cpu'
Provides-Extra: dev
Requires-Dist: black; extra == 'dev'
Requires-Dist: flake8; extra == 'dev'
Requires-Dist: pytest-cov; extra == 'dev'
Requires-Dist: pytest>=6.0; extra == 'dev'
Requires-Dist: sphinx; extra == 'dev'
Requires-Dist: sphinx-rtd-theme; extra == 'dev'
